streamer/__init__.py
streamer/collector.py
streamer/operator.py
streamer/stream.py
streamer/streams.py
streamer/util.py
pystreamer-0.4.3.dist-info/LICENSE
pystreamer-0.4.3.dist-info/METADATA
pystreamer-0.4.3.dist-info/WHEEL
pystreamer-0.4.3.dist-info/top_level.txt
pystreamer-0.4.3.dist-info/RECORD
